TOPSIS_Vishal_101803152
