Metadata-Version: 2.1
Name: TOPSIS-Vishal-101803152
Version: 0.4
Summary: Topsis Assignment
Home-page: https://github.com/vishal-gulati/TOPSIS_Vishal_101803152
Author: Vishal Gulati
Author-email: vgulati_be18@thapar.edu
License: UNKNOWN
Download-URL: https://github.com/vishal-gulati/TOPSIS_Vishal_101803152/archive/v_04.tar.gz
Platform: UNKNOWN
Classifier: Programming Language :: Python :: 3
Classifier: License :: OSI Approved :: MIT License
Classifier: Operating System :: OS Independent
